main.py
golu-0.1.0.dist-info/METADATA
golu-0.1.0.dist-info/WHEEL
golu-0.1.0.dist-info/entry_points.txt
golu-0.1.0.dist-info/top_level.txt
golu-0.1.0.dist-info/RECORD
