Metadata-Version: 2.1
Name: golu
Version: 0.1.0
Requires-Dist: Click
